drf_firebase/__init__.py
drf_firebase/apps.py
drf_firebase/authentication.py
drf_firebase_authentication-1.0.1.dist-info/LICENSE
drf_firebase_authentication-1.0.1.dist-info/METADATA
drf_firebase_authentication-1.0.1.dist-info/WHEEL
drf_firebase_authentication-1.0.1.dist-info/top_level.txt
drf_firebase_authentication-1.0.1.dist-info/RECORD
