Metadata-Version: 2.1
Name: drf-firebase-authentication
Version: 1.0.1
Summary: A flexible Django Rest Framework Firebase authentication class
Home-page: https://github.com/DoctorJohn/drf-firebase-authentication
Author: Jonathan Ehwald
Author-email: pypi@ehwald.info
License: MIT License
Platform: UNKNOWN
Classifier: Environment :: Web Environment
Classifier: Framework :: Django
Classifier: Framework :: Django :: 1.11
Classifier: Framework :: Django :: 2.0
Classifier: Framework :: Django :: 2.1
Classifier: Framework :: Django :: 2.2
Classifier: Intended Audience :: Developers
Classifier: License :: OSI Approved :: MIT License
Classifier: Operating System :: OS Independent
Classifier: Programming Language :: Python
Classifier: Programming Language :: Python :: 3
Classifier: Programming Language :: Python :: 3.3
Classifier: Programming Language :: Python :: 3.4
Classifier: Programming Language :: Python :: 3.5
Classifier: Programming Language :: Python :: 3.6
Classifier: Programming Language :: Python :: 3.7
Classifier: Topic :: Internet :: WWW/HTTP
Requires-Dist: firebase-admin (~=3.0.0)
Requires-Dist: djangorestframework (>=3.1)
Requires-Dist: Django (>=1.11)
